Workbook

Sheet Assumptions
A7: Key Assumptions
A8: Purchase Equity Value ($m) | B8: 1500
A9: Net Debt at Close ($m) | B9: 300
A10: Transaction Costs (% EV) | B10: 1.5
A11: Revenue Year 1 ($m) | B11: 1200
A12: Revenue Growth (%) | B12: 4.5
A13: EBITDA Margin (%) | B13: 18
A14: Synergy EBITDA Uplift (%) | B14: 2
A15: Depreciation (% Revenue) | B15: 2.5
A16: Capex (% Revenue) | B16: 3
A17: Working Capital (% Revenue) | B17: 4
A18: Tax Rate (%) | B18: 30
A19: WACC (%) | B19: 8.5
... A21: Exit EBITDA Multiple | B21: 9

Sheet Forecast
A6: Year | B6: 1 | C6: 2 | D6: 3 | E6: 4 | F6: 5 | G6: 6 | H6: 7 | I6: 8 | J6: 9 | K6: 10
A7: Revenue | B7: =IF(1=1,Assumptions!B11,A7*(1+Assumptions!B12/100)) -> 1200 | C7: =IF(2=1,Assumptions!B11,B7*(1+Assumptions!B12/100)) -> 1254 | D7: =IF(3=1,Assumptions!B11,C7*(1+Assumptions!B12/100)) -> 1310.43 | E7: =IF(4=1,Assumptions!B11,D7*(1+Assumptions!B12/100)) -> 1369.3993 | F7: =IF(5=1,Assumptions!B11,E7*(1+Assumptions!B12/100)) -> 1431.0223 | G7: =IF(6=1,Assumptions!B11,F7*(1+Assumptions!B12/100)) -> 1495.4183 | H7: =IF(7=1,Assumptions!B11,G7*(1+Assumptions!B12/100)) -> 1562.7122 | I7: =IF(8=1,Assumptions!B11,H7*(1+Assumptions!B12/100)) -> 1633.0342 | J7: =IF(9=1,Assumptions!B11,I7*(1+Assumptions!B12/100)) -> 1706.5207 | K7: =IF(10=1,Assumptions!B11,J7*(1+Assumptions!B12/100)) -> 1783.3142
A8: EBITDA (Standalone) | B8: =B7*Assumptions!B13/100 -> 216 | C8: =C7*Assumptions!B13/100 -> 225.72 | D8: =D7*Assumptions!B13/100 -> 235.8774 | E8: =E7*Assumptions!B13/100 -> 246.49188 | F8: =F7*Assumptions!B13/100 -> 257.58402 | G8: =G7*Assumptions!B13/100 -> 269.1753 | H8: =H7*Assumptions!B13/100 -> 281.28819 | I8: =I7*Assumptions!B13/100 -> 293.94616 | J8: =J7*Assumptions!B13/100 -> 307.17373 | K8: =K7*Assumptions!B13/100 -> 320.99655
A9: Synergy EBITDA | B9: =B8*Assumptions!B14/100 -> 4.32 | C9: =C8*Assumptions!B14/100 -> 4.5144 | D9: =D8*Assumptions!B14/100 -> 4.717548 | E9: =E8*Assumptions!B14/100 -> 4.9298377 | F9: =F8*Assumptions!B14/100 -> 5.1516804 | G9: =G8*Assumptions!B14/100 -> 5.383506 | H9: =H8*Assumptions!B14/100 -> 5.6257637 | I9: =I8*Assumptions!B14/100 -> 5.8789231 | J9: =J8*Assumptions!B14/100 -> 6.1434746 | K9: =K8*Assumptions!B14/100 -> 6.419931
A10: EBITDA (Total) | B10: =B8+B9 -> 220.32 | C10: =C8+C9 -> 230.2344 | D10: =D8+D9 -> 240.59495 | E10: =E8+E9 -> 251.42172 | F10: =F8+F9 -> 262.7357 | G10: =G8+G9 -> 274.5588 | H10: =H8+H9 -> 286.91395 | I10: =I8+I9 -> 299.82508 | ... K10: =K8+K9 -> 327.41648
A11: Depreciation | B11: =B7*Assumptions!B15/100 -> 30 | C11: =C7*Assumptions!B15/100 -> 31.35 | D11: =D7*Assumptions!B15/100 -> 32.76075 | E11: =E7*Assumptions!B15/100 -> 34.234984 | F11: =F7*Assumptions!B15/100 -> 35.775558 | G11: =G7*Assumptions!B15/100 -> 37.385458 | H11: =H7*Assumptions!B15/100 -> 39.067804 | I11: =I7*Assumptions!B15/100 -> 40.825855 | J11: =J7*Assumptions!B15/100 -> 42.663018 | K11: =K7*Assumptions!B15/100 -> 44.582854
A12: EBIT | B12: =B10-B11 -> 190.32 | C12: =C10-C11 -> 198.8844 | D12: =D10-D11 -> 207.8342 | E12: =E10-E11 -> 217.18674 | F12: =F10-F11 -> 226.96014 | G12: =G10-G11 -> 237.17335 | H12: =H10-H11 -> 247.84615 | I12: =I10-I11 -> 258.99922 | ... K12: =K10-K11 -> 282.83363
A13: Tax | B13: =-B12*Assumptions!B18/100 -> -57.096 | C13: =-C12*Assumptions!B18/100 -> -59.66532 | D13: =-D12*Assumptions!B18/100 -> -62.350259 | E13: =-E12*Assumptions!B18/100 -> -65.156021 | F13: =-F12*Assumptions!B18/100 -> -68.088042 | G13: =-G12*Assumptions!B18/100 -> -71.152004 | H13: =-H12*Assumptions!B18/100 -> -74.353844 | I13: =-I12*Assumptions!B18/100 -> -77.699767 | J13: =-J12*Assumptions!B18/100 -> -81.196257 | K13: =-K12*Assumptions!B18/100 -> -84.850088
A14: NOPAT | B14: =B12+B13 -> 133.224 | C14: =C12+C13 -> 139.21908 | D14: =D12+D13 -> 145.48394 | E14: =E12+E13 -> 152.03072 | F14: =F12+F13 -> 158.8721 | G14: =G12+G13 -> 166.02134 | H14: =H12+H13 -> 173.4923 | I14: =I12+I13 -> 181.29946 | ... K14: =K12+K13 -> 197.98354
A15: Capex | B15: =-B7*Assumptions!B16/100 -> -36 | C15: =-C7*Assumptions!B16/100 -> -37.62 | D15: =-D7*Assumptions!B16/100 -> -39.3129 | E15: =-E7*Assumptions!B16/100 -> -41.081981 | F15: =-F7*Assumptions!B16/100 -> -42.93067 | G15: =-G7*Assumptions!B16/100 -> -44.86255 | H15: =-H7*Assumptions!B16/100 -> -46.881364 | I15: =-I7*Assumptions!B16/100 -> -48.991026 | J15: =-J7*Assumptions!B16/100 -> -51.195622 | K15: =-K7*Assumptions!B16/100 -> -53.499425
A16: Change in Working Capital | B16: =-(B7-Assumptions!B11)*Assumptions!B17/100 -> 0 | C16: =-(C7-Assumptions!B11)*Assumptions!B17/100 -> -2.16 | D16: =-(D7-Assumptions!B11)*Assumptions!B17/100 -> -4.4172 | E16: =-(E7-Assumptions!B11)*Assumptions!B17/100 -> -6.775974 | F16: =-(F7-Assumptions!B11)*Assumptions!B17/100 -> -9.2408928 | G16: =-(G7-Assumptions!B11)*Assumptions!B17/100 -> -11.816733 | H16: =-(H7-Assumptions!B11)*Assumptions!B17/100 -> -14.508486 | I16: =-(I7-Assumptions!B11)*Assumptions!B17/100 -> -17.321368 | J16: =-(J7-Assumptions!B11)*Assumptions!B17/100 -> -20.260829 | K16: =-(K7-Assumptions!B11)*Assumptions!B17/100 -> -23.332567
A17: Free Cash Flow | B17: =B14+B11+B15+B16 -> 127.224 | C17: =C14+C11+C15+C16 -> 130.78908 | D17: =D14+D11+D15+D16 -> 134.51459 | E17: =E14+E11+E15+E16 -> 138.40775 | F17: =F14+F11+F15+F16 -> 142.47609 | G17: =G14+G11+G15+G16 -> 146.72752 | H17: =H14+H11+H15+H16 -> 151.17026 | I17: =I14+I11+I15+I16 -> 155.81292 | ... K17: =K14+K11+K15+K16 -> 165.7344

Sheet Valuation
A6: DCF Valuation
A8: Year | B8: FCF | C8: Discount Factor | D8: PV
A9: 1 | B9: =Forecast!B17 -> 127.224 | C9: =1/(1+Assumptions!B19/100)^1 -> 0.92165899 | D9: =B9*C9 -> 117.25714
A10: 2 | B10: =Forecast!C17 -> 130.78908 | C10: =1/(1+Assumptions!B19/100)^2 -> 0.84945529 | D10: =B10*C10 -> 111.09948
A11: 3 | B11: =Forecast!D17 -> 134.51459 | C11: =1/(1+Assumptions!B19/100)^3 -> 0.7829081 | D11: =B11*C11 -> 105.31256
A12: 4 | B12: =Forecast!E17 -> 138.40775 | C12: =1/(1+Assumptions!B19/100)^4 -> 0.72157428 | D12: =B12*C12 -> 99.87147
A13: 5 | B13: =Forecast!F17 -> 142.47609 | C13: =1/(1+Assumptions!B19/100)^5 -> 0.66504542 | D13: =B13*C13 -> 94.753074
A14: 6 | B14: =Forecast!G17 -> 146.72752 | C14: =1/(1+Assumptions!B19/100)^6 -> 0.61294509 | D14: =B14*C14 -> 89.935912
A15: 7 | B15: =Forecast!H17 -> 151.17026 | C15: =1/(1+Assumptions!B19/100)^7 -> 0.56492635 | D15: =B15*C15 -> 85.400061
A16: 8 | B16: =Forecast!I17 -> 155.81292 | C16: =1/(1+Assumptions!B19/100)^8 -> 0.52066945 | D16: =B16*C16 -> 81.127026
A17: 9 | B17: =Forecast!J17 -> 160.6645 | C17: =1/(1+Assumptions!B19/100)^9 -> 0.47987968 | D17: =B17*C17 -> 77.099628
A18: 10 | B18: =Forecast!K17 -> 165.7344 | C18: =1/(1+Assumptions!B19/100)^10 -> 0.44228542 | D18: =B18*C18 -> 73.301909
A20: Terminal Value | B20: =B18*(1+Assumptions!B20/100)/(Assumptions!B19/100-Assumptions!B20/100) -> 2831.296 | D20: =B20/(1+Assumptions!B19/100)^10 -> 1252.2409
A22: Enterprise Value | D22: =SUM(D9:D18)+D20 -> 2187.3992
A23: Equity Value | D23: =D22-Assumptions!B9 -> 1887.3992
A24: NPV vs Purchase | D24: =D23-Assumptions!B8 -> 387.39919

Sheet Returns
A1: Equity Returns
A3: Year | B3: Equity Cash Flow
B4: =-Assumptions!B8 -> -1500
B5: 0
B6: 0
B7: 0
B8: 0
B9: 0
B10: 0
B11: 0
B12: 0
B13: 0
B14: =Valuation!D23 -> 1887.3992
A16: IRR | B16: =IRR(B4:B14) -> 0.023239391
A17: MOIC | B17: =B14/ABS(B4) -> 1.2582661

Sheet Sensitivities
A6: NPV Sensitivity ($m)
A8: WACC \ TG | B8: 2 | C8: 2.5 | D8: 3
A9: 7.5 | B9: =Valuation!D24 -> 387.39919 | C9: =Valuation!D24 -> 387.39919 | D9: =Valuation!D24 -> 387.39919
A10: 8 | B10: =Valuation!D24 -> 387.39919 | C10: =Valuation!D24 -> 387.39919 | D10: =Valuation!D24 -> 387.39919
A11: 8.5 | B11: =Valuation!D24 -> 387.39919 | C11: =Valuation!D24 -> 387.39919 | D11: =Valuation!D24 -> 387.39919
A12: 9 | B12: =Valuation!D24 -> 387.39919 | C12: =Valuation!D24 -> 387.39919 | D12: =Valuation!D24 -> 387.39919
A13: 9.5 | B13: =Valuation!D24 -> 387.39919 | C13: =Valuation!D24 -> 387.39919 | D13: =Valuation!D24 -> 387.39919

Sheet IC Summary
A1: Investment Committee Summary
A3: Target | B3: Petbarn
A4: Investment Type | B4: 100% Acquisition
A5: Equity Purchase ($m) | B5: =Assumptions!B8 -> 1500
A6: Enterprise Value ($m) | B6: =Valuation!D22 -> 2187.3992
A7: Base Case NPV ($m) | B7: =Valuation!D24 -> 387.39919
A8: IRR | B8: =Returns!B16 -> 0.023239391
A9: MOIC | B9: =Returns!B17 -> 1.2582661
A10: Key Value Drivers | B10: Margin stability, private label, supply chain leverage
A11: Key Risks | B11: Discretionary spend softness, online competition
A12: IC Recommendation | B12: Proceed subject to diligence
